[
    {
        "archivo_musica": "Albums/198274412_1.flac",
        "descripcion": "198274412",
        "imagen": "Albums/198274412.jpg",
        "genero": "Pop",
        "titulo": "Za Intro",
        "artista": "Gym Class Heroes",
        "album": "The Papercut Chronicles II [Clean]",
        "numero_de_pista": "1/11",
        "Año": "2011"
    },
    {
        "archivo_musica": "Albums/198274412_2.flac",
        "descripcion": "198274412",
        "imagen": "Albums/198274412.jpg",
        "genero": "Pop",
        "titulo": "Martyrial Girl$",
        "artista": "Gym Class Heroes",
        "album": "The Papercut Chronicles II [Clean]",
        "numero_de_pista": "2/11",
        "Año": "2011"
    },
    {
        "archivo_musica": "Albums/198274412_3.flac",
        "descripcion": "198274412",
        "imagen": "Albums/198274412.jpg",
        "genero": "Pop",
        "titulo": "Life Goes On (feat. Oh Land)",
        "artista": "Gym Class Heroes feat. Oh Land",
        "album": "The Papercut Chronicles II [Clean]",
        "numero_de_pista": "3/11",
        "Año": "2011"
    },
    {
        "archivo_musica": "Albums/198274412_4.flac",
        "descripcion": "198274412",
        "imagen": "Albums/198274412.jpg",
        "genero": "Pop",
        "titulo": "Stereo Hearts (feat. Adam Levine)",
        "artista": "Gym Class Heroes feat. Adam Levine",
        "album": "The Papercut Chronicles II [Clean]",
        "numero_de_pista": "4/11",
        "Año": "2011"
    },
    {
        "archivo_musica": "Albums/198274412_5.flac",
        "descripcion": "198274412",
        "imagen": "Albums/198274412.jpg",
        "genero": "Pop",
        "titulo": "Solo Discotheque (Whiskey Bitness) [Clean]",
        "artista": "Gym Class Heroes",
        "album": "The Papercut Chronicles II [Clean]",
        "numero_de_pista": "5/11",
        "Año": "2011"
    },
    {
        "archivo_musica": "Albums/198274412_6.flac",
        "descripcion": "198274412",
        "imagen": "Albums/198274412.jpg",
        "genero": "Pop",
        "titulo": "Holy Horseshit, Batman!",
        "artista": "Gym Class Heroes",
        "album": "The Papercut Chronicles II [Clean]",
        "numero_de_pista": "6/11",
        "Año": "2011"
    },
    {
        "archivo_musica": "Albums/198274412_7.flac",
        "descripcion": "198274412",
        "imagen": "Albums/198274412.jpg",
        "genero": "Pop",
        "titulo": "Ass Back Home (feat. Neon Hitch)",
        "artista": "Gym Class Heroes feat. Neon Hitch",
        "album": "The Papercut Chronicles II [Clean]",
        "numero_de_pista": "7/11",
        "Año": "2011"
    },
    {
        "archivo_musica": "Albums/198274412_8.flac",
        "descripcion": "198274412",
        "imagen": "Albums/198274412.jpg",
        "genero": "Pop",
        "titulo": "Nil-Nil-Draw",
        "artista": "Gym Class Heroes",
        "album": "The Papercut Chronicles II [Clean]",
        "numero_de_pista": "8/11",
        "Año": "2011"
    },
    {
        "archivo_musica": "Albums/198274412_9.flac",
        "descripcion": "198274412",
        "imagen": "Albums/198274412.jpg",
        "genero": "Pop",
        "titulo": "Lazarus, Ze Gitan [Clean]",
        "artista": "Gym Class Heroes",
        "album": "The Papercut Chronicles II [Clean]",
        "numero_de_pista": "9/11",
        "Año": "2011"
    },
    {
        "archivo_musica": "Albums/198274412_10.flac",
        "descripcion": "198274412",
        "imagen": "Albums/198274412.jpg",
        "genero": "Pop",
        "titulo": "The Fighter (feat. Ryan Tedder)",
        "artista": "Gym Class Heroes",
        "album": "The Papercut Chronicles II [Clean]",
        "numero_de_pista": "10/11",
        "Año": "2011"
    },
    {
        "archivo_musica": "Albums/198274412_11.flac",
        "descripcion": "198274412",
        "imagen": "Albums/198274412.jpg",
        "genero": "Pop",
        "titulo": "Kid Nothing and the Never-Ending Naked Nightmare",
        "artista": "Gym Class Heroes",
        "album": "The Papercut Chronicles II [Clean]",
        "numero_de_pista": "11/11",
        "Año": "2011"
    },
    {
        "archivo_musica": "Albums/198274413_1.flac",
        "descripcion": "198274413",
        "imagen": "Albums/198274413.jpg",
        "genero": "Pop/General",
        "titulo": "Tribute",
        "artista": "John Newman",
        "album": "Tribute (Deluxe)",
        "numero_de_pista": "1/15",
        "Año": "2013"
    },
    {
        "archivo_musica": "Albums/198274413_2.flac",
        "descripcion": "198274413",
        "imagen": "Albums/198274413.jpg",
        "genero": "Pop/General",
        "titulo": "Love Me Again",
        "artista": "John Newman",
        "album": "Tribute (Deluxe)",
        "numero_de_pista": "2/15",
        "Año": "2013"
    },
    {
        "archivo_musica": "Albums/198274413_3.flac",
        "descripcion": "198274413",
        "imagen": "Albums/198274413.jpg",
        "genero": "Pop/General",
        "titulo": "Losing Sleep",
        "artista": "John Newman",
        "album": "Tribute (Deluxe)",
        "numero_de_pista": "3/15",
        "Año": "2013"
    },
    {
        "archivo_musica": "Albums/198274413_4.flac",
        "descripcion": "198274413",
        "imagen": "Albums/198274413.jpg",
        "genero": "Pop/General",
        "titulo": "Easy",
        "artista": "John Newman",
        "album": "Tribute (Deluxe)",
        "numero_de_pista": "4/15",
        "Año": "2013"
    },
    {
        "archivo_musica": "Albums/198274413_5.flac",
        "descripcion": "198274413",
        "imagen": "Albums/198274413.jpg",
        "genero": "Pop/General",
        "titulo": "Try",
        "artista": "John Newman",
        "album": "Tribute (Deluxe)",
        "numero_de_pista": "5/15",
        "Año": "2013"
    },
    {
        "archivo_musica": "Albums/198274413_6.flac",
        "descripcion": "198274413",
        "imagen": "Albums/198274413.jpg",
        "genero": "Pop/General",
        "titulo": "Out Of My Head",
        "artista": "John Newman",
        "album": "Tribute (Deluxe)",
        "numero_de_pista": "6/15",
        "Año": "2013"
    },
    {
        "archivo_musica": "Albums/198274413_7.flac",
        "descripcion": "198274413",
        "imagen": "Albums/198274413.jpg",
        "genero": "Pop/General",
        "titulo": "Cheating",
        "artista": "John Newman",
        "album": "Tribute (Deluxe)",
        "numero_de_pista": "7/15",
        "Año": "2013"
    },
    {
        "archivo_musica": "Albums/198274413_8.flac",
        "descripcion": "198274413",
        "imagen": "Albums/198274413.jpg",
        "genero": "Pop/General",
        "titulo": "Running",
        "artista": "John Newman",
        "album": "Tribute (Deluxe)",
        "numero_de_pista": "8/15",
        "Año": "2013"
    },
    {
        "archivo_musica": "Albums/198274413_9.flac",
        "descripcion": "198274413",
        "imagen": "Albums/198274413.jpg",
        "genero": "Pop/General",
        "titulo": "Gold Dust",
        "artista": "John Newman",
        "album": "Tribute (Deluxe)",
        "numero_de_pista": "9/15",
        "Año": "2013"
    },
    {
        "archivo_musica": "Albums/198274413_10.flac",
        "descripcion": "198274413",
        "imagen": "Albums/198274413.jpg",
        "genero": "Pop/General",
        "titulo": "Goodnight Goodbye",
        "artista": "John Newman",
        "album": "Tribute (Deluxe)",
        "numero_de_pista": "10/15",
        "Año": "2013"
    },
    {
        "archivo_musica": "Albums/198274413_11.flac",
        "descripcion": "198274413",
        "imagen": "Albums/198274413.jpg",
        "genero": "Pop/General",
        "titulo": "All I Need Is You",
        "artista": "John Newman",
        "album": "Tribute (Deluxe)",
        "numero_de_pista": "11/15",
        "Año": "2013"
    },
    {
        "archivo_musica": "Albums/198274413_12.flac",
        "descripcion": "198274413",
        "imagen": "Albums/198274413.jpg",
        "genero": "Pop/General",
        "titulo": "Down The Line",
        "artista": "John Newman",
        "album": "Tribute (Deluxe)",
        "numero_de_pista": "12/15",
        "Año": "2013"
    },
    {
        "archivo_musica": "Albums/198274413_13.flac",
        "descripcion": "198274413",
        "imagen": "Albums/198274413.jpg",
        "genero": "Pop/General",
        "titulo": "Nothing",
        "artista": "John Newman",
        "album": "Tribute (Deluxe)",
        "numero_de_pista": "13/15",
        "Año": "2013"
    },
    {
        "archivo_musica": "Albums/198274413_14.flac",
        "descripcion": "198274413",
        "imagen": "Albums/198274413.jpg",
        "genero": "Pop/General",
        "titulo": "Day One [Explicit]",
        "artista": "John Newman",
        "album": "Tribute (Deluxe)",
        "numero_de_pista": "14/15",
        "Año": "2013"
    },
    {
        "archivo_musica": "Albums/198274413_15.flac",
        "descripcion": "198274413",
        "imagen": "Albums/198274413.jpg",
        "genero": "Pop/General",
        "titulo": "Out Of My Head (Club Edit)",
        "artista": "John Newman",
        "album": "Tribute (Deluxe)",
        "numero_de_pista": "15/15",
        "Año": "2013"
    },
    {
        "archivo_musica": "Albums/198274414_1.flac",
        "descripcion": "198274414",
        "imagen": "Albums/198274414.jpg",
        "genero": "Pop/General",
        "titulo": "Revolve [feat. Idris Elba]",
        "artista": "John Newman feat. Idris Elba",
        "album": "Revolve",
        "numero_de_pista": "1/11",
        "Año": "2015"
    },
    {
        "archivo_musica": "Albums/198274414_2.flac",
        "descripcion": "198274414",
        "imagen": "Albums/198274414.jpg",
        "genero": "Pop/General",
        "titulo": "All My Heart",
        "artista": "John Newman",
        "album": "Revolve",
        "numero_de_pista": "2/11",
        "Año": "2015"
    },
    {
        "archivo_musica": "Albums/198274414_3.flac",
        "descripcion": "198274414",
        "imagen": "Albums/198274414.jpg",
        "genero": "Pop/General",
        "titulo": "Something Special",
        "artista": "John Newman",
        "album": "Revolve",
        "numero_de_pista": "3/11",
        "Año": "2015"
    },
    {
        "archivo_musica": "Albums/198274414_4.flac",
        "descripcion": "198274414",
        "imagen": "Albums/198274414.jpg",
        "genero": "Pop/General",
        "titulo": "Lights Down",
        "artista": "John Newman",
        "album": "Revolve",
        "numero_de_pista": "4/11",
        "Año": "2015"
    },
    {
        "archivo_musica": "Albums/198274414_5.flac",
        "descripcion": "198274414",
        "imagen": "Albums/198274414.jpg",
        "genero": "Pop/General",
        "titulo": "Come And Get It",
        "artista": "John Newman",
        "album": "Revolve",
        "numero_de_pista": "5/11",
        "Año": "2015"
    },
    {
        "archivo_musica": "Albums/198274414_6.flac",
        "descripcion": "198274414",
        "imagen": "Albums/198274414.jpg",
        "genero": "Pop/General",
        "titulo": "Never Give It Up",
        "artista": "John Newman",
        "album": "Revolve",
        "numero_de_pista": "6/11",
        "Año": "2015"
    },
    {
        "archivo_musica": "Albums/198274414_7.flac",
        "descripcion": "198274414",
        "imagen": "Albums/198274414.jpg",
        "genero": "Pop/General",
        "titulo": "Tiring Game [feat. Charlie Wilson]",
        "artista": "John Newman feat. Charlie Wilson",
        "album": "Revolve",
        "numero_de_pista": "7/11",
        "Año": "2015"
    },
    {
        "archivo_musica": "Albums/198274414_8.flac",
        "descripcion": "198274414",
        "imagen": "Albums/198274414.jpg",
        "genero": "Pop/General",
        "titulo": "Give You My Love",
        "artista": "John Newman",
        "album": "Revolve",
        "numero_de_pista": "8/11",
        "Año": "2015"
    },
    {
        "archivo_musica": "Albums/198274414_9.flac",
        "descripcion": "198274414",
        "imagen": "Albums/198274414.jpg",
        "genero": "Pop/General",
        "titulo": "I'm Not Your Man",
        "artista": "John Newman",
        "album": "Revolve",
        "numero_de_pista": "9/11",
        "Año": "2015"
    },
    {
        "archivo_musica": "Albums/198274414_10.flac",
        "descripcion": "198274414",
        "imagen": "Albums/198274414.jpg",
        "genero": "Pop/General",
        "titulo": "Killing Me",
        "artista": "John Newman",
        "album": "Revolve",
        "numero_de_pista": "10/11",
        "Año": "2015"
    },
    {
        "archivo_musica": "Albums/198274414_11.flac",
        "descripcion": "198274414",
        "imagen": "Albums/198274414.jpg",
        "genero": "Pop/General",
        "titulo": "We All Get Lonely",
        "artista": "John Newman",
        "album": "Revolve",
        "numero_de_pista": "11/11",
        "Año": "2015"
    },
    {
        "archivo_musica": "Albums/198274415_1.flac",
        "descripcion": "198274415",
        "imagen": "Albums/198274415.jpg",
        "genero": "Dance & DJ/General",
        "titulo": "Reload (Radio Edit)",
        "artista": "Sebastian Ingrosso, Tommy Trash & John Martin",
        "album": "Reload (Remixes)",
        "numero_de_pista": "1/4",
        "Año": "2013"
    },
    {
        "archivo_musica": "Albums/198274415_2.flac",
        "descripcion": "198274415",
        "imagen": "Albums/198274415.jpg",
        "genero": "Dance & DJ/General",
        "titulo": "Reload (Extended Mix) [feat. John Martin]",
        "artista": "Sebastian Ingrosso & Tommy Trash feat. John Martin",
        "album": "Reload (Remixes)",
        "numero_de_pista": "2/4",
        "Año": "2012"
    },
    {
        "archivo_musica": "Albums/198274415_3.flac",
        "descripcion": "198274415",
        "imagen": "Albums/198274415.jpg",
        "genero": "Dance & DJ/General",
        "titulo": "Reload (Instrumental Mix)",
        "artista": "Sebastian Ingrosso & Tommy Trash",
        "album": "Reload (Remixes)",
        "numero_de_pista": "3/4",
        "Año": "2013"
    },
    {
        "archivo_musica": "Albums/198274415_4.flac",
        "descripcion": "198274415",
        "imagen": "Albums/198274415.jpg",
        "genero": "Dance & DJ/General",
        "titulo": "Reload (Tiedye Remix)",
        "artista": "Sebastian Ingrosso, Tommy Trash & John Martin",
        "album": "Reload (Remixes)",
        "numero_de_pista": "4/4",
        "Año": "2013"
    },
    {
        "archivo_musica": "Albums/198274416_1.flac",
        "descripcion": "198274416",
        "imagen": "Albums/198274416.jpg",
        "genero": "Dance & DJ",
        "titulo": "Home (feat. Sinéad Harnett)",
        "artista": "Rudimental feat. Sinéad Harnett",
        "album": "Home (10th Anniversary Edition) [Explicit]",
        "numero_de_pista": "1/21",
        "Año": "2013"
    },
    {
        "archivo_musica": "Albums/198274416_2.flac",
        "descripcion": "198274416",
        "imagen": "Albums/198274416.jpg",
        "genero": "Dance & DJ/Electronica",
        "titulo": "Feel the Love (feat. John Newman)",
        "artista": "Rudimental feat. John Newman",
        "album": "Home (10th Anniversary Edition) [Explicit]",
        "numero_de_pista": "2/21",
        "Año": "2012"
    },
    {
        "archivo_musica": "Albums/198274416_3.flac",
        "descripcion": "198274416",
        "imagen": "Albums/198274416.jpg",
        "genero": "Dance & DJ",
        "titulo": "Right Here (feat. Foxes)",
        "artista": "Rudimental feat. Foxes",
        "album": "Home (10th Anniversary Edition) [Explicit]",
        "numero_de_pista": "3/21",
        "Año": "2013"
    },
    {
        "archivo_musica": "Albums/198274416_4.flac",
        "descripcion": "198274416",
        "imagen": "Albums/198274416.jpg",
        "genero": "Dance & DJ",
        "titulo": "Hell Could Freeze (feat. Angel Haze) [Explicit]",
        "artista": "Rudimental feat. Angel Haze",
        "album": "Home (10th Anniversary Edition) [Explicit]",
        "numero_de_pista": "4/21",
        "Año": "2013"
    },
    {
        "archivo_musica": "Albums/198274416_5.flac",
        "descripcion": "198274416",
        "imagen": "Albums/198274416.jpg",
        "genero": "Dance & DJ",
        "titulo": "Spoons (feat. MNEK & Syron)",
        "artista": "Rudimental feat. Mnek & Syron",
        "album": "Home (10th Anniversary Edition) [Explicit]",
        "numero_de_pista": "5/21",
        "Año": "2012"
    },
    {
        "archivo_musica": "Albums/198274416_6.flac",
        "descripcion": "198274416",
        "imagen": "Albums/198274416.jpg",
        "genero": "Dance & DJ",
        "titulo": "Hide (feat. Sinéad Harnett)",
        "artista": "Rudimental feat. Sinéad Harnett",
        "album": "Home (10th Anniversary Edition) [Explicit]",
        "numero_de_pista": "6/21",
        "Año": "2013"
    },
    {
        "archivo_musica": "Albums/198274416_7.flac",
        "descripcion": "198274416",
        "imagen": "Albums/198274416.jpg",
        "genero": "Dance & DJ",
        "titulo": "Powerless (feat. Becky Hill)",
        "artista": "Rudimental feat. Becky Hill",
        "album": "Home (10th Anniversary Edition) [Explicit]",
        "numero_de_pista": "7/21",
        "Año": "2013"
    },
    {
        "archivo_musica": "Albums/198274416_8.flac",
        "descripcion": "198274416",
        "imagen": "Albums/198274416.jpg",
        "genero": "Dance & DJ",
        "titulo": "More Than Anything (feat. Emeli Sandé)",
        "artista": "Rudimental feat. Emeli Sandé",
        "album": "Home (10th Anniversary Edition) [Explicit]",
        "numero_de_pista": "8/21",
        "Año": "2013"
    },
    {
        "archivo_musica": "Albums/198274416_9.flac",
        "descripcion": "198274416",
        "imagen": "Albums/198274416.jpg",
        "genero": "Dance & DJ",
        "titulo": "Not Giving In (feat. John Newman & Alex Clare)",
        "artista": "Rudimental feat. John Newman & Alex Clare",
        "album": "Home (10th Anniversary Edition) [Explicit]",
        "numero_de_pista": "9/21",
        "Año": "2012"
    },
    {
        "archivo_musica": "Albums/198274416_10.flac",
        "descripcion": "198274416",
        "imagen": "Albums/198274416.jpg",
        "genero": "Dance & DJ",
        "titulo": "Baby (feat. MNEK & Sinéad Harnett)",
        "artista": "Rudimental feat. Mnek & Sinéad Harnett",
        "album": "Home (10th Anniversary Edition) [Explicit]",
        "numero_de_pista": "10/21",
        "Año": "2013"
    },
    {
        "archivo_musica": "Albums/198274416_11.flac",
        "descripcion": "198274416",
        "imagen": "Albums/198274416.jpg",
        "genero": "Dance & DJ",
        "titulo": "Waiting All Night (feat. Ella Eyre)",
        "artista": "Rudimental feat. Ella Eyre",
        "album": "Home (10th Anniversary Edition) [Explicit]",
        "numero_de_pista": "11/21",
        "Año": "2013"
    },
    {
        "archivo_musica": "Albums/198274416_12.flac",
        "descripcion": "198274416",
        "imagen": "Albums/198274416.jpg",
        "genero": "Dance & DJ",
        "titulo": "Free (feat. Emeli Sandé)",
        "artista": "Rudimental feat. Emeli Sandé",
        "album": "Home (10th Anniversary Edition) [Explicit]",
        "numero_de_pista": "12/21",
        "Año": "2013"
    },
    {
        "archivo_musica": "Albums/198274416_13.flac",
        "descripcion": "198274416",
        "imagen": "Albums/198274416.jpg",
        "genero": "Dance & DJ",
        "titulo": "Give You Up (feat. Alex Clare)",
        "artista": "Rudimental feat. Alex Clare",
        "album": "Home (10th Anniversary Edition) [Explicit]",
        "numero_de_pista": "13/21",
        "Año": "2013"
    },
    {
        "archivo_musica": "Albums/198274416_14.flac",
        "descripcion": "198274416",
        "imagen": "Albums/198274416.jpg",
        "genero": "Dance & DJ",
        "titulo": "Alien Bashment",
        "artista": "Rudimental",
        "album": "Home (10th Anniversary Edition) [Explicit]",
        "numero_de_pista": "14/21",
        "Año": "2013"
    },
    {
        "archivo_musica": "Albums/198274416_15.flac",
        "descripcion": "198274416",
        "imagen": "Albums/198274416.jpg",
        "genero": "Dance & DJ",
        "titulo": "Solo (feat. Ella Eyre & Mark Crown)",
        "artista": "Rudimental feat. Ella Eyre & mark crown",
        "album": "Home (10th Anniversary Edition) [Explicit]",
        "numero_de_pista": "15/21",
        "Año": "2013"
    },
    {
        "archivo_musica": "Albums/198274416_16.flac",
        "descripcion": "198274416",
        "imagen": "Albums/198274416.jpg",
        "genero": "Dance & DJ",
        "titulo": "Feel the Love (feat. John Newman) [Rudimental VIP]",
        "artista": "Rudimental feat. John Newman",
        "album": "Home (10th Anniversary Edition) [Explicit]",
        "numero_de_pista": "16/21",
        "Año": "2013"
    },
    {
        "archivo_musica": "Albums/198274416_17.flac",
        "descripcion": "198274416",
        "imagen": "Albums/198274416.jpg",
        "genero": "Dance & DJ",
        "titulo": "More Than Anything (feat. Emeli Sandé) [CLIPZ - Joy & Pain Remix]",
        "artista": "Rudimental feat. Emeli Sandé",
        "album": "Home (10th Anniversary Edition) [Explicit]",
        "numero_de_pista": "17/21",
        "Año": "2023"
    },
    {
        "archivo_musica": "Albums/198274416_18.flac",
        "descripcion": "198274416",
        "imagen": "Albums/198274416.jpg",
        "genero": "Dance & DJ",
        "titulo": "Home (feat. Sinéad Harnett) [Special Request Remix]",
        "artista": "Rudimental feat. Sinéad Harnett",
        "album": "Home (10th Anniversary Edition) [Explicit]",
        "numero_de_pista": "18/21",
        "Año": "2023"
    },
    {
        "archivo_musica": "Albums/198274416_19.flac",
        "descripcion": "198274416",
        "imagen": "Albums/198274416.jpg",
        "genero": "Dance & DJ",
        "titulo": "Hide (feat. Sinéad Harnett) [Interplanetary Criminal Remix]",
        "artista": "Rudimental feat. Sinéad Harnett",
        "album": "Home (10th Anniversary Edition) [Explicit]",
        "numero_de_pista": "19/21",
        "Año": "2023"
    },
    {
        "archivo_musica": "Albums/198274416_20.flac",
        "descripcion": "198274416",
        "imagen": "Albums/198274416.jpg",
        "genero": "Dance & DJ",
        "titulo": "Spoons (feat. MNEK & Syron) [CERCA Remix]",
        "artista": "Rudimental feat. Mnek & Syron",
        "album": "Home (10th Anniversary Edition) [Explicit]",
        "numero_de_pista": "20/21",
        "Año": "2023"
    },
    {
        "archivo_musica": "Albums/198274416_21.flac",
        "descripcion": "198274416",
        "imagen": "Albums/198274416.jpg",
        "genero": "Dance & DJ",
        "titulo": "Alien Bashment (Chris Stussy Remix)",
        "artista": "Rudimental",
        "album": "Home (10th Anniversary Edition) [Explicit]",
        "numero_de_pista": "21/21",
        "Año": "2023"
    },
    {
        "archivo_musica": "Albums/198274417_1.flac",
        "descripcion": "198274417",
        "imagen": "Albums/198274417.jpg",
        "genero": "International/Far East & Asia",
        "titulo": "Again",
        "artista": "YUI",
        "album": "again",
        "numero_de_pista": "1/4",
        "Año": "2009"
    },
    {
        "archivo_musica": "Albums/198274417_2.flac",
        "descripcion": "198274417",
        "imagen": "Albums/198274417.jpg",
        "genero": "International/Far East & Asia",
        "titulo": "Sea",
        "artista": "YUI",
        "album": "again",
        "numero_de_pista": "2/4",
        "Año": "2009"
    },
    {
        "archivo_musica": "Albums/198274417_3.flac",
        "descripcion": "198274417",
        "imagen": "Albums/198274417.jpg",
        "genero": "International/Far East & Asia",
        "titulo": "Summer Song (Yui Acoustic Version)",
        "artista": "YUI",
        "album": "again",
        "numero_de_pista": "3/4",
        "Año": "2009"
    },
    {
        "archivo_musica": "Albums/198274417_4.flac",
        "descripcion": "198274417",
        "imagen": "Albums/198274417.jpg",
        "genero": "International/Far East & Asia",
        "titulo": "Again (Instrumental)",
        "artista": "YUI",
        "album": "again",
        "numero_de_pista": "4/4",
        "Año": "2009"
    }
]